abcdi/__init__.py
abcdi/context.py
abcdi-0.7.0.dist-info/licenses/LICENSE
abcdi-0.7.0.dist-info/METADATA
abcdi-0.7.0.dist-info/WHEEL
abcdi-0.7.0.dist-info/top_level.txt
abcdi-0.7.0.dist-info/RECORD
