Metadata-Version: 2.4
Name: abcdi
Version: 0.7.0
Summary: A simple, lightweight dependency injection library for Python based on constructor parameter name matching.
Requires-Python: >=3.13
License-File: LICENSE
Dynamic: license-file
